CHANGELOG.md
futon/__init__.py
futon/brokers/__init__.py
futon/brokers/coindcx.py
futon/brokers/local.py
futon/data/__init__.py
futon/data/helpers.py
futon/data/providers.py
futon/indicators.py
futon/instruments.py
futon/strategy/__init__.py
futon/strategy/helpers.py
futon/viz.py
futon-1.0.0.dist-info/LICENSE
futon-1.0.0.dist-info/WHEEL
futon-1.0.0.dist-info/METADATA
futon-1.0.0.dist-info/RECORD
