Metadata-Version: 2.1
Name: futon
Version: 1.0.0
Summary: Create automated bots that trade for you while you sleep
Home-page: https://github.com/agrawal-rohit/futon
License: GPL-3.0-only
Keywords: Stocks,Cryptocurrencies,Algorithmic Trading,Backtesting,Trading bots
Author: Rohit Agrawal
Author-email: rohitagrawalofficialmail@gmail.com
Requires-Python: >=3.7,<4.0
Classifier: Development Status :: 4 - Beta
Classifier: Intended Audience :: Financial and Insurance Industry
Classifier: License :: OSI Approved :: GNU General Public License v3 (GPLv3)
Classifier: Programming Language :: Python :: 3
Classifier: Programming Language :: Python :: 3.7
Classifier: Programming Language :: Python :: 3.8
Classifier: Programming Language :: Python :: 3.9
Classifier: Topic :: Scientific/Engineering :: Artificial Intelligence
Classifier: Topic :: Software Development :: Libraries :: Python Modules
Requires-Dist: Requests (==2.25.1)
Requires-Dist: TA_Lib (==0.4.20)
Requires-Dist: binance (==0.3)
Requires-Dist: bokeh (==2.3.2)
Requires-Dist: numpy (>=1.20.3,<2.0.0)
Requires-Dist: pandas (>=1.1.5,<2.0.0)
Requires-Dist: python_binance (==1.0.10)
Requires-Dist: tqdm (==4.61.1)
Requires-Dist: websocket_client (==1.1.0)
Project-URL: Documentation, https://github.com/agrawal-rohit/futon
Project-URL: Repository, https://github.com/agrawal-rohit/futon
